{
    "trial_id": "18",
    "model_type": "vit",
    "image_size": 128,
    "batch_size": 200,
    "epochs": 10,
    "num_classes": 4,
    "loss": "mse",
    "code_name": "Echo Hartebeest",
    "isolate_nodule_image": false,
    "detection": true,
    "static_params": false,
    "score": [
        0.10637537389993668,
        0.399115651845932
    ],
    "score_names": [
        "loss",
        "bounding_box_intersection_over_union_tf"
    ],
    "x_train_size": 15048,
    "y_train_size": 15048,
    "x_valid_size": 3135,
    "y_valid_size": 3135,
    "image_channels": 1,
    "version": 1,
    "data_transformer_name": "bbox",
    "history": {
        "loss": [
            0.11220003664493561,
            0.1107448935508728,
            0.11043284088373184,
            0.11012852936983109,
            0.10944698005914688,
            0.10907351970672607,
            0.10876773297786713,
            0.10861280560493469,
            0.10833605378866196,
            0.10813470929861069
        ],
        "bounding_box_intersection_over_union_tf": [
            0.38710474967956543,
            0.39191871881484985,
            0.39400890469551086,
            0.394157350063324,
            0.39550042152404785,
            0.39563456177711487,
            0.3962765336036682,
            0.3964221477508545,
            0.3970993757247925,
            0.3971932530403137
        ],
        "val_loss": [
            0.10911619663238525,
            0.10870441049337387,
            0.10873044282197952,
            0.10787850618362427,
            0.1076284795999527,
            0.10691177845001221,
            0.10690347850322723,
            0.10661780089139938,
            0.10654506832361221,
            0.10637537389993668
        ],
        "val_bounding_box_intersection_over_union_tf": [
            0.39117562770843506,
            0.3946368992328644,
            0.3903242349624634,
            0.39443129301071167,
            0.3934716582298279,
            0.40010976791381836,
            0.3968815505504608,
            0.40116995573043823,
            0.40158960223197937,
            0.3991156816482544
        ]
    },
    "learning_params": {
        "learning_rate": 1.4040405606755107e-05,
        "projection_dim": 128,
        "num_heads": 4,
        "drop_out_1": 0.04344832768607372,
        "drop_out_2": 0.05059006557872941,
        "drop_out_3": 0.1649757612420524,
        "transformer_layers": 4,
        "patch_size": 8,
        "activation": "softmax",
        "weight": 0.003009264724101271,
        "momentum": 2.190060535263753e-08,
        "optimizer": "Adam"
    }
}
