{
    "trial_id": "7",
    "model_type": "vit",
    "image_size": 128,
    "batch_size": 200,
    "epochs": 10,
    "num_classes": 4,
    "loss": "mse",
    "code_name": "Echo Hartebeest",
    "isolate_nodule_image": false,
    "detection": true,
    "static_params": false,
    "score": [
        0.11094243824481964,
        0.37806436419487
    ],
    "score_names": [
        "loss",
        "bounding_box_intersection_over_union_tf"
    ],
    "x_train_size": 15048,
    "y_train_size": 15048,
    "x_valid_size": 3135,
    "y_valid_size": 3135,
    "image_channels": 1,
    "version": 1,
    "data_transformer_name": "bbox",
    "history": {
        "loss": [
            0.11205992102622986,
            0.1120126023888588,
            0.11201319098472595,
            0.11201281100511551,
            0.1120130866765976,
            0.1120130717754364,
            0.11201314628124237,
            0.11201285570859909,
            0.11201312392950058,
            0.11201246082782745
        ],
        "bounding_box_intersection_over_union_tf": [
            0.3778488337993622,
            0.37785738706588745,
            0.37785446643829346,
            0.3778567314147949,
            0.37785521149635315,
            0.37785524129867554,
            0.3778548538684845,
            0.3778562843799591,
            0.3778550624847412,
            0.37785789370536804
        ],
        "val_loss": [
            0.11093828827142715,
            0.11094032227993011,
            0.11093847453594208,
            0.11094026267528534,
            0.11094051599502563,
            0.11094063520431519,
            0.11093884706497192,
            0.11093992739915848,
            0.11093968152999878,
            0.11094240844249725
        ],
        "val_bounding_box_intersection_over_union_tf": [
            0.37808313965797424,
            0.3780735731124878,
            0.37808260321617126,
            0.37807419896125793,
            0.3780728578567505,
            0.37807247042655945,
            0.3780810832977295,
            0.3780757784843445,
            0.37807729840278625,
            0.3780643343925476
        ]
    },
    "learning_params": {
        "learning_rate": 0.011403383772630006,
        "projection_dim": 76,
        "num_heads": 2,
        "drop_out_1": 0.2816305967384094,
        "drop_out_2": 0.03379217379084343,
        "drop_out_3": 0.052388711130912834,
        "transformer_layers": 3,
        "patch_size": 32,
        "activation": "softmax",
        "weight": 0.08161908197954673,
        "momentum": 5.6110717917516725e-06,
        "optimizer": "SGDW"
    }
}
